README.md
setup.cfg
setup.py
consign/__init__.py
consign/__version__.py
consign/adapters.py
consign/api.py
consign/exceptions.py
consign/models.py
consign/sessions.py
consign.egg-info/PKG-INFO
consign.egg-info/SOURCES.txt
consign.egg-info/dependency_links.txt
consign.egg-info/not-zip-safe
consign.egg-info/requires.txt
consign.egg-info/top_level.txt