Metadata-Version: 2.1
Name: consign
Version: 0.1.4
Summary: Python storage for humans.
Home-page: https://requests.readthedocs.io
Author: Daniel Jadraque
Author-email: jadraque@hey.com
License: Apache 2.0
Project-URL: Source, https://github.com/jadraque/consign
Platform: UNKNOWN
Classifier: Development Status :: 1 - Planning
Classifier: Intended Audience :: Developers
Classifier: Natural Language :: English
Classifier: License :: OSI Approved :: Apache Software License
Classifier: Programming Language :: Python :: 3.6
Classifier: Programming Language :: Python :: 3.7
Classifier: Programming Language :: Python :: 3.8
Classifier: Programming Language :: Python :: 3.9
Requires-Python: >=2.7, !=3.0.*, !=3.1.*, !=3.2.*, !=3.3.*, !=3.4.*
